tests/__init__.py
tests/test_util_1c_rac.py
util_1c_rac-0.4.1.dist-info/METADATA
util_1c_rac-0.4.1.dist-info/WHEEL
util_1c_rac-0.4.1.dist-info/entry_points.txt
util_1c_rac/__init__.py
util_1c_rac/rac.py
util_1c_rac/utils.py
util_1c_rac-0.4.1.dist-info/RECORD
