Metadata-Version: 2.1
Name: util-1c-rac
Version: 0.4.1
Summary: Utils for 1C:Enterprise Remote Administration Client
Author-Email: Cujoko <cujoko@gmail.com>, George Kvelidze <georgiykvelidze@gmail.com>
License: MIT
Classifier: Development Status :: 4 - Beta
Classifier: Intended Audience :: Developers
Classifier: License :: OSI Approved :: MIT License
Classifier: Natural Language :: Russian
Classifier: Programming Language :: Python :: 3.14
Classifier: Programming Language :: Python :: 3.13
Classifier: Programming Language :: Python :: 3.12
Classifier: Programming Language :: Python :: 3.11
Classifier: Programming Language :: Python :: 3.10
Classifier: Topic :: Software Development
Classifier: Topic :: Utilities
Project-URL: repository, https://github.com/Cujoko-Dev/util-1c-rac
Requires-Python: >=3.10
Requires-Dist: commons-1c<4.0.0,>=3.6.2
Requires-Dist: loguru>=0.6.0
Requires-Dist: pyyaml>=6.0
